python_jmap/__init__.py
python_jmap/__main__.py
python_jmap/py.typed
python_jmap/types/__init__.py
python_jmap/types/date.py
python_jmap/types/id.py
python_jmap/types/int.py
python_jmap-0.0.4.dist-info/LICENSE
python_jmap-0.0.4.dist-info/WHEEL
python_jmap-0.0.4.dist-info/METADATA
python_jmap-0.0.4.dist-info/entry_points.txt
python_jmap-0.0.4.dist-info/RECORD
