Metadata-Version: 2.1
Name: python-jmap
Version: 0.0.4
Summary: Python JMAP Bindings
Home-page: https://github.com/boopmail/python-jmap
License: MIT
Author: Josh Finch
Author-email: josh@boop.email
Requires-Python: >=3.8,<4.0
Classifier: Development Status :: 1 - Planning
Classifier: License :: OSI Approved :: MIT License
Classifier: Programming Language :: Python :: 3
Classifier: Programming Language :: Python :: 3.8
Classifier: Programming Language :: Python :: 3.9
Classifier: Programming Language :: Python :: 3.10
Classifier: Programming Language :: Python :: 3.11
Requires-Dist: pydantic (>=2.0.2,<3.0.0)
Project-URL: Changelog, https://github.com/boopmail/python-jmap/releases
Project-URL: Documentation, https://python-jmap.readthedocs.io
Project-URL: Repository, https://github.com/boopmail/python-jmap
